moodlerpd/__init__.py
moodlerpd/main.py
moodlerpd/client/__init__.py
moodlerpd/client/client_service.py
moodlerpd/client/info_handler.py
moodlerpd/client/request_client.py
moodlerpd/client/results_handler.py
moodlerpd/config/__init__.py
moodlerpd/config/config_service.py
moodlerpd/downloads/__init__.py
moodlerpd/downloads/download_service.py
moodlerpd/downloads/downloader.py
moodlerpd/downloads/fake_download_service.py
moodlerpd/downloads/url_target.py
moodlerpd/state/__init__.py
moodlerpd/state/category.py
moodlerpd/state/course.py
moodlerpd/state/file.py
moodlerpd/state/state_service.py
moodlerpd/utils/__init__.py
moodlerpd/utils/path_tools.py
moodlerpd/utils/process_lock.py
moodlerpd-0.1.8.dist-info/METADATA
moodlerpd-0.1.8.dist-info/WHEEL
moodlerpd-0.1.8.dist-info/entry_points.txt
moodlerpd-0.1.8.dist-info/top_level.txt
moodlerpd-0.1.8.dist-info/RECORD
