Metadata-Version: 2.1
Name: moodlerpd
Version: 0.1.8
Summary: moodlerpd that downloads course content fast from moodle
Home-page: UNKNOWN
License: UNKNOWN
Platform: UNKNOWN
Requires-Python: >=3.6
Requires-Dist: certifi (>=2020.4.5.2)
Requires-Dist: colorama (>=0.4.3)
Requires-Dist: html2text (>=2020.1.16)
Requires-Dist: readchar (>=2.0.1)
Requires-Dist: requests (>=2.24.0)
Requires-Dist: setuptools (~=45.2.0)
Requires-Dist: youtube-dl (>=2020.9.20)
